PyOptionPane/__init__.py
PyOptionPane/src/__init__.py
PyOptionPane/src/pyoptionpane.py
PyOptionPane-1.0.2.dist-info/LICENSE
PyOptionPane-1.0.2.dist-info/METADATA
PyOptionPane-1.0.2.dist-info/WHEEL
PyOptionPane-1.0.2.dist-info/top_level.txt
PyOptionPane-1.0.2.dist-info/RECORD
