Metadata-Version: 2.1
Name: PyOptionPane
Version: 1.0.2
Summary: Python GUIs made easy!
Home-page: https://github.com/yavda1/PyOptionPane
Author: yavda1
License: MIT
Classifier: License :: OSI Approved :: MIT License
Classifier: Programming Language :: Python :: 3.10
Classifier: Operating System :: OS Independent
Requires-Python: >=3.10
License-File: LICENSE
Requires-Dist: tk
Requires-Dist: pillow
Requires-Dist: requests
Provides-Extra: dev
Requires-Dist: pytest (>=7.0) ; extra == 'dev'
Requires-Dist: twine (>=4.0.2) ; extra == 'dev'
